tkstylesheet/__init__.py
tkstylesheet/tkstylesheet.py
tkstylesheet-0.0.1b0.dist-info/LICENSE
tkstylesheet-0.0.1b0.dist-info/METADATA
tkstylesheet-0.0.1b0.dist-info/WHEEL
tkstylesheet-0.0.1b0.dist-info/top_level.txt
tkstylesheet-0.0.1b0.dist-info/RECORD
