Metadata-Version: 2.1
Name: tkstylesheet
Version: 0.0.1b0
Summary: This library helps you to set style to tkinter default widget using stylesheet with ease.
Home-page: https://github.com/PaulleDemon/tkStyleSheet
Author: Paul
License: MIT
Keywords: tkinter,stylesheet,tkss,tkinter stylesheet
Platform: UNKNOWN
Classifier: License :: OSI Approved :: MIT License
Classifier: Development Status :: 4 - Beta
Classifier: Programming Language :: Python :: 3.6
Classifier: Programming Language :: Python :: 3.7
Classifier: Programming Language :: Python :: 3.8
Classifier: Programming Language :: Python :: 3.9
Classifier: Programming Language :: Python :: 3.10
Requires-Python: >=3.6
